{"br": {"country_name": "Brasil", "last_update": "2024-10-23 19:07:15"}, "cn": {"country_name": "China", "last_update": "2024-10-23 19:07:13"}, "de": {"country_name": "German", "last_update": "2024-10-23 19:07:13"}, "fr": {"country_name": "Franch", "last_update": "2024-10-23 19:03:28"}, "gb": {"country_name": "United Kingdom", "last_update": "2024-10-23 19:04:11"}, "il": {"country_name": "Israel", "last_update": "2024-10-23 19:03:28"}, "in": {"country_name": "India", "last_update": "2024-10-23 19:06:55"}, "jp": {"country_name": "Japan", "last_update": "2024-10-23 19:00:08"}, "kr": {"country_name": "Korea", "last_update": "2024-10-23 19:00:02"}, "lb": {"country_name": "Lebanon", "last_update": "2024-10-23 19:00:08"}, "pl": {"country_name": "Poland", "last_update": "2024-10-23 19:03:16"}, "ru": {"country_name": "Russia", "last_update": "2024-10-23 19:00:05"}, "tw": {"country_name": "Taiwan", "last_update": "2024-10-23 19:00:05"}, "us": {"country_name": "United States", "last_update": "2024-10-23 19:03:26"}}