{"br": {"country_name": "Brasil", "last_update": "2024-11-13 15:00:09"}, "cn": {"country_name": "China", "last_update": "2024-11-13 15:00:10"}, "de": {"country_name": "German", "last_update": "2024-11-13 15:00:11"}, "fr": {"country_name": "Franch", "last_update": "2024-11-13 15:00:10"}, "gb": {"country_name": "United Kingdom", "last_update": "2024-11-13 15:00:11"}, "il": {"country_name": "Israel", "last_update": "2024-11-13 15:07:06"}, "in": {"country_name": "India", "last_update": "2024-11-13 15:07:22"}, "jp": {"country_name": "Japan", "last_update": "2024-11-13 15:07:21"}, "kr": {"country_name": "Korea", "last_update": "2024-11-13 15:07:10"}, "lb": {"country_name": "Lebanon", "last_update": "2024-11-13 15:03:20"}, "pl": {"country_name": "Poland", "last_update": "2024-11-13 15:03:21"}, "ru": {"country_name": "Russia", "last_update": "2024-11-13 15:03:33"}, "tw": {"country_name": "Taiwan", "last_update": "2024-11-13 15:03:31"}, "us": {"country_name": "United States", "last_update": "2024-11-13 15:03:51"}}